PairTripleDetector.v
//========================================================================
// PairTripleDetector
//========================================================================

module PairTripleDetector
(
  input  wire in0,
  input  wire in1,
  input  wire in2,
  output wire out
);

  wire w;
  wire y;
  wire x;
  or (  w, in0, in1);
  and(  x, in0, in1);
  and(  y,   w, in2);
  or (out,   y,   x);

endmodule

src/ece2300-stdlib.v
//========================================================================
// ece2300-stdlib
//========================================================================
// ECE 2300 standard library for lab assignments.

`ifndef ECE2300_STDLIB_V
`define ECE2300_STDLIB_V

module ece2300_TestUtils
(
  output logic clk,
  output logic reset
);

  initial clk = 1'b1;
  always #5 clk = ~clk;

  // Error count

  string pass_fail = "\n*** PASSED ***\n";
  int num_errors = 0;

  // This variable holds the +test-case command line argument indicating
  // which test cases to run.

  string vcd_filename;
  int n = 0;
  initial begin

    if ( !$value$plusargs( "test-case=%d", n ) )
      n = 0;

    if ( $value$plusargs( "dump-vcd=%s", vcd_filename ) ) begin
      $dumpfile(vcd_filename);
      $dumpvars();
    end

  end

  // Always call $urandom with this seed variable to ensure that random
  // test cases are both isolated and reproducible.

  int seed = 32'hdeadbeef;

  // Cycle counter with timeout check

  int cycles;

  always @( posedge clk ) begin

    if ( reset )
      cycles <= 0;
    else
      cycles <= cycles + 1;

    if ( cycles > 10000 ) begin
      pass_fail = "\n*** FAILED ***\n";
      num_errors = num_errors + 1;
      $display( "  ERROR (cycles=%0d): timeout!\n", cycles );
      $finish;
    end

  end

  // reset

  task reset_sequence();
    seed = 32'hdeadbeef;

    reset = 1;
    #30;
    reset = 0;
  endtask

endmodule

//------------------------------------------------------------------------
// ECE2300_CHECK_EQ
//------------------------------------------------------------------------
// Compare two expressions which can be signals or constants. We use the
// XOR operator so that an X in __ref will match 0, 1, or X in __dut, but
// an X in __dut will only match an X in __ref.

`define ECE2300_CHECK_EQ( __dut, __ref )                                \
  if ( __ref !== ( __ref ^ __dut ^ __ref ) ) begin                      \
    t.pass_fail = "\n*** FAILED ***\n";                                 \
    t.num_errors = t.num_errors + 1;                                    \
    $display( "  ERROR (cycle=%0d): %s != %s (%x != %x)",               \
              t.cycles, "__dut", "__ref", __dut, __ref );               \
  end                                                                   \
  if (1)

`endif /* ECE2300_STDLIB */

PairTripleDetector_test.v
//========================================================================
// PairTripleDetector_test
//========================================================================

`include "ece2300-stdlib.v"

module Top();

  //----------------------------------------------------------------------
  // Setup
  //----------------------------------------------------------------------

  logic clk;
  logic reset;

  ece2300_TestUtils t( .* );

  //----------------------------------------------------------------------
  // Instantiate design under test
  //----------------------------------------------------------------------

  logic dut_in0;
  logic dut_in1;
  logic dut_in2;
  logic dut_out;

  PairTripleDetector dut
  (
    .in0 (dut_in0),
    .in1 (dut_in1),
    .in2 (dut_in2),
    .out (dut_out)
  );

  //----------------------------------------------------------------------
  // check
  //----------------------------------------------------------------------
  // All tasks start at #1 after the rising edge of the clock. So we
  // write the inputs #1 after the rising edge, and check the outputs #1
  // before the next rising edge.

  task check
  (
    input logic in0,
    input logic in1,
    input logic in2,
    input logic out
  );

    dut_in0 = in0;
    dut_in1 = in1;
    dut_in2 = in2;

    #8;

    if ( t.n != 0 )
      $display( "%3d: %x %x %x > %x", t.cycles,
                dut_in0, dut_in1, dut_in2, dut_out );

    `ECE2300_CHECK_EQ( dut_out, out );

    #2;

  endtask

  //----------------------------------------------------------------------
  // test_case_1_basic
  //----------------------------------------------------------------------

  task test_case_1_basic();
    $display( "\ntest_case_1_basic" );
    t.reset_sequence();

    check( 0, 0, 0, 0 );
    check( 0, 1, 1, 1 );
    check( 0, 1, 0, 0 );
    check( 1, 1, 1, 1 );

  endtask

  //----------------------------------------------------------------------
  // test_case_2_exhaustive
  //----------------------------------------------------------------------

  task test_case_2_exhaustive();
    $display( "\ntest_case_2_exhaustive" );
    t.reset_sequence();

    check( 0, 0, 0, 0 );
    check( 0, 0, 1, 0 );
    check( 0, 1, 0, 0 );
    check( 0, 1, 1, 1 );

    check( 1, 0, 0, 0 );
    check( 1, 0, 1, 1 );
    check( 1, 1, 0, 1 );
    check( 1, 1, 1, 1 );

  endtask

  //----------------------------------------------------------------------
  // main
  //----------------------------------------------------------------------
  // We start with a #1 delay so that all tasks will essentially start at
  // #1 after the rising edge of the clock.

  initial begin
    #1;

    if ((t.n <= 0) || (t.n == 1)) test_case_1_basic();
    if ((t.n <= 0) || (t.n == 2)) test_case_2_exhaustive();

    $display(t.pass_fail);
    $finish;
  end

endmodule

PairTripleDetector_test.vcd
$date
	Fri Sep  6 14:52:34 2024
$end
$version
	Icarus Verilog
$end
$timescale
	1s
$end
$scope module Top $end
$var wire 1 ! reset $end
$var wire 1 " dut_out $end
$var wire 1 # clk $end
$var reg 1 $ dut_in0 $end
$var reg 1 % dut_in1 $end
$var reg 1 & dut_in2 $end
$scope module dut $end
$var wire 1 $ in0 $end
$var wire 1 % in1 $end
$var wire 1 & in2 $end
$var wire 1 " out $end
$var wire 1 ' w $end
$var wire 1 ( x $end
$var wire 1 ) y $end
$upscope $end
$scope module t $end
$var reg 1 # clk $end
$var reg 1 ! reset $end
$var integer 32 * cycles [31:0] $end
$var integer 32 + n [31:0] $end
$var integer 32 , num_errors [31:0] $end
$var integer 32 - seed [31:0] $end
$scope task reset_sequence $end
$upscope $end
$upscope $end
$scope task check $end
$var reg 1 . in0 $end
$var reg 1 / in1 $end
$var reg 1 0 in2 $end
$var reg 1 1 out $end
$upscope $end
$scope task test_case_1_basic $end
$upscope $end
$scope task test_case_2_exhaustive $end
$upscope $end
$upscope $end
$enddefinitions $end
$comment Show the parameter values. $end
$dumpall
$end
#0
$dumpvars
x1
x0
x/
x.
b11011110101011011011111011101111 -
b0 ,
b10 +
b0 *
x)
x(
x'
x&
x%
x$
1#
x"
x!
$end
#1
1!
#5
0#
#10
1#
#15
0#
#20
1#
#25
0#
#30
1#
#31
0"
0)
0'
0(
0&
0%
0$
01
00
0/
0.
0!
#35
0#
#40
b1 *
1#
#41
1&
10
#45
0#
#50
b10 *
1#
#51
1'
0&
1%
00
1/
#55
0#
#60
b11 *
1#
#61
1"
1)
1&
11
10
#65
0#
#70
b100 *
1#
#71
0"
0)
0&
0%
1$
01
00
0/
1.
#75
0#
#80
b101 *
1#
#81
1"
1)
1&
11
10
#85
0#
#90
b110 *
1#
#91
0)
1(
0&
1%
00
1/
#95
0#
#100
b111 *
1#
#101
1)
1&
10
#105
0#
#110
b1000 *
1#
